[{"x":1,"y":5,"sx":"0.1","sy":"0.5","c":1},
{"x":1,"y":6,"sx":"0.1","sy":"0.6","c":2},
{"x":1,"y":7,"sx":"0.1","sy":"0.7","c":4},
{"x":1,"y":9,"sx":"0.1","sy":"0.9","c":4},
{"x":1,"y":10,"sx":"0.1","sy":"1.0","c":3},
{"x":1,"y":11,"sx":"0.1","sy":"1.1","c":3},
{"x":1,"y":12,"sx":"0.1","sy":"1.2","c":8},
{"x":1,"y":13,"sx":"0.1","sy":"1.3","c":1},
{"x":1,"y":14,"sx":"0.1","sy":"1.4","c":1},
{"x":1,"y":15,"sx":"0.1","sy":"1.5","c":4},
{"x":1,"y":16,"sx":"0.1","sy":"1.6","c":1},
{"x":1,"y":18,"sx":"0.1","sy":"1.8","c":1},
{"x":1,"y":19,"sx":"0.1","sy":"1.9","c":2},
{"x":1,"y":20,"sx":"0.1","sy":"2.0","c":2},
{"x":1,"y":21,"sx":"0.1","sy":"2.1","c":2},
{"x":1,"y":22,"sx":"0.1","sy":"2.2","c":2},
{"x":1,"y":23,"sx":"0.1","sy":"2.3","c":1},
{"x":1,"y":24,"sx":"0.1","sy":"2.4","c":2},
{"x":1,"y":25,"sx":"0.1","sy":"2.5","c":5},
{"x":1,"y":26,"sx":"0.1","sy":"2.6","c":1},
{"x":1,"y":27,"sx":"0.1","sy":"2.7","c":1},
{"x":2,"y":6,"sx":"0.2","sy":"0.6","c":15},
{"x":2,"y":7,"sx":"0.2","sy":"0.7","c":10},
{"x":2,"y":8,"sx":"0.2","sy":"0.8","c":12},
{"x":2,"y":9,"sx":"0.2","sy":"0.9","c":6},
{"x":2,"y":10,"sx":"0.2","sy":"1.0","c":12},
{"x":2,"y":11,"sx":"0.2","sy":"1.1","c":12},
{"x":2,"y":12,"sx":"0.2","sy":"1.2","c":9},
{"x":2,"y":13,"sx":"0.2","sy":"1.3","c":8},
{"x":2,"y":14,"sx":"0.2","sy":"1.4","c":6},
{"x":2,"y":15,"sx":"0.2","sy":"1.5","c":3},
{"x":2,"y":16,"sx":"0.2","sy":"1.6","c":2},
{"x":2,"y":17,"sx":"0.2","sy":"1.7","c":6},
{"x":2,"y":18,"sx":"0.2","sy":"1.8","c":4},
{"x":2,"y":19,"sx":"0.2","sy":"1.9","c":8},
{"x":2,"y":20,"sx":"0.2","sy":"2.0","c":7},
{"x":2,"y":21,"sx":"0.2","sy":"2.1","c":5},
{"x":2,"y":22,"sx":"0.2","sy":"2.2","c":7},
{"x":2,"y":23,"sx":"0.2","sy":"2.3","c":3},
{"x":2,"y":24,"sx":"0.2","sy":"2.4","c":13},
{"x":2,"y":25,"sx":"0.2","sy":"2.5","c":7},
{"x":2,"y":27,"sx":"0.2","sy":"2.7","c":1},
{"x":2,"y":33,"sx":"0.2","sy":"3.3","c":1},
{"x":2,"y":45,"sx":"0.2","sy":"4.5","c":1},
{"x":3,"y":6,"sx":"0.3","sy":"0.6","c":11},
{"x":3,"y":7,"sx":"0.3","sy":"0.7","c":27},
{"x":3,"y":8,"sx":"0.3","sy":"0.8","c":27},
{"x":3,"y":9,"sx":"0.3","sy":"0.9","c":15},
{"x":3,"y":10,"sx":"0.3","sy":"1.0","c":13},
{"x":3,"y":11,"sx":"0.3","sy":"1.1","c":13},
{"x":3,"y":12,"sx":"0.3","sy":"1.2","c":20},
{"x":3,"y":13,"sx":"0.3","sy":"1.3","c":20},
{"x":3,"y":14,"sx":"0.3","sy":"1.4","c":19},
{"x":3,"y":15,"sx":"0.3","sy":"1.5","c":10},
{"x":3,"y":16,"sx":"0.3","sy":"1.6","c":9},
{"x":3,"y":17,"sx":"0.3","sy":"1.7","c":8},
{"x":3,"y":18,"sx":"0.3","sy":"1.8","c":2},
{"x":3,"y":19,"sx":"0.3","sy":"1.9","c":9},
{"x":3,"y":20,"sx":"0.3","sy":"2.0","c":3},
{"x":3,"y":21,"sx":"0.3","sy":"2.1","c":12},
{"x":3,"y":22,"sx":"0.3","sy":"2.2","c":20},
{"x":3,"y":23,"sx":"0.3","sy":"2.3","c":7},
{"x":3,"y":24,"sx":"0.3","sy":"2.4","c":6},
{"x":3,"y":25,"sx":"0.3","sy":"2.5","c":4},
{"x":3,"y":26,"sx":"0.3","sy":"2.6","c":4},
{"x":3,"y":27,"sx":"0.3","sy":"2.7","c":4},
{"x":3,"y":28,"sx":"0.3","sy":"2.8","c":2},
{"x":3,"y":29,"sx":"0.3","sy":"2.9","c":1},
{"x":3,"y":30,"sx":"0.3","sy":"3.0","c":1},
{"x":3,"y":33,"sx":"0.3","sy":"3.3","c":1},
{"x":3,"y":34,"sx":"0.3","sy":"3.4","c":2},
{"x":3,"y":42,"sx":"0.3","sy":"4.2","c":1},
{"x":3,"y":69,"sx":"0.3","sy":"6.9","c":1},
{"x":4,"y":6,"sx":"0.4","sy":"0.6","c":4},
{"x":4,"y":7,"sx":"0.4","sy":"0.7","c":67},
{"x":4,"y":8,"sx":"0.4","sy":"0.8","c":58},
{"x":4,"y":9,"sx":"0.4","sy":"0.9","c":41},
{"x":4,"y":10,"sx":"0.4","sy":"1.0","c":20},
{"x":4,"y":11,"sx":"0.4","sy":"1.1","c":26},
{"x":4,"y":12,"sx":"0.4","sy":"1.2","c":14},
{"x":4,"y":13,"sx":"0.4","sy":"1.3","c":31},
{"x":4,"y":14,"sx":"0.4","sy":"1.4","c":17},
{"x":4,"y":15,"sx":"0.4","sy":"1.5","c":12},
{"x":4,"y":16,"sx":"0.4","sy":"1.6","c":17},
{"x":4,"y":17,"sx":"0.4","sy":"1.7","c":15},
{"x":4,"y":18,"sx":"0.4","sy":"1.8","c":24},
{"x":4,"y":19,"sx":"0.4","sy":"1.9","c":17},
{"x":4,"y":20,"sx":"0.4","sy":"2.0","c":17},
{"x":4,"y":21,"sx":"0.4","sy":"2.1","c":16},
{"x":4,"y":22,"sx":"0.4","sy":"2.2","c":20},
{"x":4,"y":23,"sx":"0.4","sy":"2.3","c":9},
{"x":4,"y":24,"sx":"0.4","sy":"2.4","c":10},
{"x":4,"y":25,"sx":"0.4","sy":"2.5","c":8},
{"x":4,"y":26,"sx":"0.4","sy":"2.6","c":6},
{"x":4,"y":28,"sx":"0.4","sy":"2.8","c":3},
{"x":4,"y":29,"sx":"0.4","sy":"2.9","c":1},
{"x":4,"y":31,"sx":"0.4","sy":"3.1","c":1},
{"x":4,"y":33,"sx":"0.4","sy":"3.3","c":2},
{"x":4,"y":35,"sx":"0.4","sy":"3.5","c":1},
{"x":4,"y":38,"sx":"0.4","sy":"3.8","c":1},
{"x":5,"y":7,"sx":"0.5","sy":"0.7","c":16},
{"x":5,"y":8,"sx":"0.5","sy":"0.8","c":98},
{"x":5,"y":9,"sx":"0.5","sy":"0.9","c":60},
{"x":5,"y":10,"sx":"0.5","sy":"1.0","c":52},
{"x":5,"y":11,"sx":"0.5","sy":"1.1","c":54},
{"x":5,"y":12,"sx":"0.5","sy":"1.2","c":36},
{"x":5,"y":13,"sx":"0.5","sy":"1.3","c":29},
{"x":5,"y":14,"sx":"0.5","sy":"1.4","c":30},
{"x":5,"y":15,"sx":"0.5","sy":"1.5","c":32},
{"x":5,"y":16,"sx":"0.5","sy":"1.6","c":26},
{"x":5,"y":17,"sx":"0.5","sy":"1.7","c":25},
{"x":5,"y":18,"sx":"0.5","sy":"1.8","c":29},
{"x":5,"y":19,"sx":"0.5","sy":"1.9","c":26},
{"x":5,"y":20,"sx":"0.5","sy":"2.0","c":26},
{"x":5,"y":21,"sx":"0.5","sy":"2.1","c":25},
{"x":5,"y":22,"sx":"0.5","sy":"2.2","c":27},
{"x":5,"y":23,"sx":"0.5","sy":"2.3","c":13},
{"x":5,"y":24,"sx":"0.5","sy":"2.4","c":14},
{"x":5,"y":25,"sx":"0.5","sy":"2.5","c":13},
{"x":5,"y":26,"sx":"0.5","sy":"2.6","c":12},
{"x":5,"y":27,"sx":"0.5","sy":"2.7","c":3},
{"x":5,"y":28,"sx":"0.5","sy":"2.8","c":3},
{"x":5,"y":29,"sx":"0.5","sy":"2.9","c":2},
{"x":5,"y":31,"sx":"0.5","sy":"3.1","c":1},
{"x":5,"y":33,"sx":"0.5","sy":"3.3","c":1},
{"x":6,"y":7,"sx":"0.6","sy":"0.7","c":2},
{"x":6,"y":8,"sx":"0.6","sy":"0.8","c":87},
{"x":6,"y":9,"sx":"0.6","sy":"0.9","c":101},
{"x":6,"y":10,"sx":"0.6","sy":"1.0","c":69},
{"x":6,"y":11,"sx":"0.6","sy":"1.1","c":69},
{"x":6,"y":12,"sx":"0.6","sy":"1.2","c":64},
{"x":6,"y":13,"sx":"0.6","sy":"1.3","c":42},
{"x":6,"y":14,"sx":"0.6","sy":"1.4","c":46},
{"x":6,"y":15,"sx":"0.6","sy":"1.5","c":40},
{"x":6,"y":16,"sx":"0.6","sy":"1.6","c":34},
{"x":6,"y":17,"sx":"0.6","sy":"1.7","c":34},
{"x":6,"y":18,"sx":"0.6","sy":"1.8","c":27},
{"x":6,"y":19,"sx":"0.6","sy":"1.9","c":31},
{"x":6,"y":20,"sx":"0.6","sy":"2.0","c":26},
{"x":6,"y":21,"sx":"0.6","sy":"2.1","c":29},
{"x":6,"y":22,"sx":"0.6","sy":"2.2","c":23},
{"x":6,"y":23,"sx":"0.6","sy":"2.3","c":21},
{"x":6,"y":24,"sx":"0.6","sy":"2.4","c":21},
{"x":6,"y":25,"sx":"0.6","sy":"2.5","c":12},
{"x":6,"y":26,"sx":"0.6","sy":"2.6","c":9},
{"x":6,"y":27,"sx":"0.6","sy":"2.7","c":8},
{"x":6,"y":28,"sx":"0.6","sy":"2.8","c":5},
{"x":6,"y":29,"sx":"0.6","sy":"2.9","c":2},
{"x":6,"y":30,"sx":"0.6","sy":"3.0","c":1},
{"x":7,"y":8,"sx":"0.7","sy":"0.8","c":32},
{"x":7,"y":9,"sx":"0.7","sy":"0.9","c":116},
{"x":7,"y":10,"sx":"0.7","sy":"1.0","c":118},
{"x":7,"y":11,"sx":"0.7","sy":"1.1","c":99},
{"x":7,"y":12,"sx":"0.7","sy":"1.2","c":81},
{"x":7,"y":13,"sx":"0.7","sy":"1.3","c":61},
{"x":7,"y":14,"sx":"0.7","sy":"1.4","c":52},
{"x":7,"y":15,"sx":"0.7","sy":"1.5","c":62},
{"x":7,"y":16,"sx":"0.7","sy":"1.6","c":53},
{"x":7,"y":17,"sx":"0.7","sy":"1.7","c":41},
{"x":7,"y":18,"sx":"0.7","sy":"1.8","c":55},
{"x":7,"y":19,"sx":"0.7","sy":"1.9","c":58},
{"x":7,"y":20,"sx":"0.7","sy":"2.0","c":34},
{"x":7,"y":21,"sx":"0.7","sy":"2.1","c":50},
{"x":7,"y":22,"sx":"0.7","sy":"2.2","c":36},
{"x":7,"y":23,"sx":"0.7","sy":"2.3","c":28},
{"x":7,"y":24,"sx":"0.7","sy":"2.4","c":35},
{"x":7,"y":25,"sx":"0.7","sy":"2.5","c":26},
{"x":7,"y":26,"sx":"0.7","sy":"2.6","c":13},
{"x":7,"y":27,"sx":"0.7","sy":"2.7","c":12},
{"x":7,"y":28,"sx":"0.7","sy":"2.8","c":12},
{"x":7,"y":29,"sx":"0.7","sy":"2.9","c":1},
{"x":7,"y":30,"sx":"0.7","sy":"3.0","c":1},
{"x":7,"y":31,"sx":"0.7","sy":"3.1","c":1},
{"x":7,"y":32,"sx":"0.7","sy":"3.2","c":1},
{"x":7,"y":44,"sx":"0.7","sy":"4.4","c":1},
{"x":8,"y":9,"sx":"0.8","sy":"0.9","c":90},
{"x":8,"y":10,"sx":"0.8","sy":"1.0","c":124},
{"x":8,"y":11,"sx":"0.8","sy":"1.1","c":119},
{"x":8,"y":12,"sx":"0.8","sy":"1.2","c":116},
{"x":8,"y":13,"sx":"0.8","sy":"1.3","c":125},
{"x":8,"y":14,"sx":"0.8","sy":"1.4","c":99},
{"x":8,"y":15,"sx":"0.8","sy":"1.5","c":88},
{"x":8,"y":16,"sx":"0.8","sy":"1.6","c":81},
{"x":8,"y":17,"sx":"0.8","sy":"1.7","c":89},
{"x":8,"y":18,"sx":"0.8","sy":"1.8","c":57},
{"x":8,"y":19,"sx":"0.8","sy":"1.9","c":86},
{"x":8,"y":20,"sx":"0.8","sy":"2.0","c":74},
{"x":8,"y":21,"sx":"0.8","sy":"2.1","c":57},
{"x":8,"y":22,"sx":"0.8","sy":"2.2","c":48},
{"x":8,"y":23,"sx":"0.8","sy":"2.3","c":43},
{"x":8,"y":24,"sx":"0.8","sy":"2.4","c":56},
{"x":8,"y":25,"sx":"0.8","sy":"2.5","c":40},
{"x":8,"y":26,"sx":"0.8","sy":"2.6","c":14},
{"x":8,"y":27,"sx":"0.8","sy":"2.7","c":15},
{"x":8,"y":28,"sx":"0.8","sy":"2.8","c":12},
{"x":8,"y":29,"sx":"0.8","sy":"2.9","c":4},
{"x":8,"y":30,"sx":"0.8","sy":"3.0","c":2},
{"x":8,"y":31,"sx":"0.8","sy":"3.1","c":4},
{"x":8,"y":32,"sx":"0.8","sy":"3.2","c":3},
{"x":8,"y":33,"sx":"0.8","sy":"3.3","c":1},
{"x":9,"y":9,"sx":"0.9","sy":"0.9","c":21},
{"x":9,"y":10,"sx":"0.9","sy":"1.0","c":127},
{"x":9,"y":11,"sx":"0.9","sy":"1.1","c":155},
{"x":9,"y":12,"sx":"0.9","sy":"1.2","c":160},
{"x":9,"y":13,"sx":"0.9","sy":"1.3","c":154},
{"x":9,"y":14,"sx":"0.9","sy":"1.4","c":168},
{"x":9,"y":15,"sx":"0.9","sy":"1.5","c":151},
{"x":9,"y":16,"sx":"0.9","sy":"1.6","c":135},
{"x":9,"y":17,"sx":"0.9","sy":"1.7","c":153},
{"x":9,"y":18,"sx":"0.9","sy":"1.8","c":134},
{"x":9,"y":19,"sx":"0.9","sy":"1.9","c":124},
{"x":9,"y":20,"sx":"0.9","sy":"2.0","c":114},
{"x":9,"y":21,"sx":"0.9","sy":"2.1","c":94},
{"x":9,"y":22,"sx":"0.9","sy":"2.2","c":90},
{"x":9,"y":23,"sx":"0.9","sy":"2.3","c":75},
{"x":9,"y":24,"sx":"0.9","sy":"2.4","c":116},
{"x":9,"y":25,"sx":"0.9","sy":"2.5","c":58},
{"x":9,"y":26,"sx":"0.9","sy":"2.6","c":48},
{"x":9,"y":27,"sx":"0.9","sy":"2.7","c":26},
{"x":9,"y":28,"sx":"0.9","sy":"2.8","c":33},
{"x":9,"y":29,"sx":"0.9","sy":"2.9","c":8},
{"x":9,"y":30,"sx":"0.9","sy":"3.0","c":4},
{"x":9,"y":31,"sx":"0.9","sy":"3.1","c":4},
{"x":9,"y":32,"sx":"0.9","sy":"3.2","c":3},
{"x":9,"y":33,"sx":"0.9","sy":"3.3","c":2},
{"x":10,"y":10,"sx":"1.0","sy":"1.0","c":22},
{"x":10,"y":11,"sx":"1.0","sy":"1.1","c":117},
{"x":10,"y":12,"sx":"1.0","sy":"1.2","c":168},
{"x":10,"y":13,"sx":"1.0","sy":"1.3","c":211},
{"x":10,"y":14,"sx":"1.0","sy":"1.4","c":225},
{"x":10,"y":15,"sx":"1.0","sy":"1.5","c":154},
{"x":10,"y":16,"sx":"1.0","sy":"1.6","c":201},
{"x":10,"y":17,"sx":"1.0","sy":"1.7","c":187},
{"x":10,"y":18,"sx":"1.0","sy":"1.8","c":128},
{"x":10,"y":19,"sx":"1.0","sy":"1.9","c":137},
{"x":10,"y":20,"sx":"1.0","sy":"2.0","c":151},
{"x":10,"y":21,"sx":"1.0","sy":"2.1","c":146},
{"x":10,"y":22,"sx":"1.0","sy":"2.2","c":126},
{"x":10,"y":23,"sx":"1.0","sy":"2.3","c":129},
{"x":10,"y":24,"sx":"1.0","sy":"2.4","c":167},
{"x":10,"y":25,"sx":"1.0","sy":"2.5","c":86},
{"x":10,"y":26,"sx":"1.0","sy":"2.6","c":67},
{"x":10,"y":27,"sx":"1.0","sy":"2.7","c":47},
{"x":10,"y":28,"sx":"1.0","sy":"2.8","c":56},
{"x":10,"y":29,"sx":"1.0","sy":"2.9","c":10},
{"x":10,"y":30,"sx":"1.0","sy":"3.0","c":10},
{"x":10,"y":31,"sx":"1.0","sy":"3.1","c":8},
{"x":10,"y":32,"sx":"1.0","sy":"3.2","c":6},
{"x":10,"y":33,"sx":"1.0","sy":"3.3","c":1},
{"x":10,"y":34,"sx":"1.0","sy":"3.4","c":2},
{"x":10,"y":36,"sx":"1.0","sy":"3.6","c":2},
{"x":10,"y":38,"sx":"1.0","sy":"3.8","c":1},
{"x":10,"y":40,"sx":"1.0","sy":"4.0","c":1},
{"x":11,"y":11,"sx":"1.1","sy":"1.1","c":11},
{"x":11,"y":12,"sx":"1.1","sy":"1.2","c":36},
{"x":11,"y":13,"sx":"1.1","sy":"1.3","c":71},
{"x":11,"y":14,"sx":"1.1","sy":"1.4","c":82},
{"x":11,"y":15,"sx":"1.1","sy":"1.5","c":88},
{"x":11,"y":16,"sx":"1.1","sy":"1.6","c":106},
{"x":11,"y":17,"sx":"1.1","sy":"1.7","c":89},
{"x":11,"y":18,"sx":"1.1","sy":"1.8","c":99},
{"x":11,"y":19,"sx":"1.1","sy":"1.9","c":70},
{"x":11,"y":20,"sx":"1.1","sy":"2.0","c":79},
{"x":11,"y":21,"sx":"1.1","sy":"2.1","c":155},
{"x":11,"y":22,"sx":"1.1","sy":"2.2","c":132},
{"x":11,"y":23,"sx":"1.1","sy":"2.3","c":88},
{"x":11,"y":24,"sx":"1.1","sy":"2.4","c":87},
{"x":11,"y":25,"sx":"1.1","sy":"2.5","c":77},
{"x":11,"y":26,"sx":"1.1","sy":"2.6","c":63},
{"x":11,"y":27,"sx":"1.1","sy":"2.7","c":44},
{"x":11,"y":28,"sx":"1.1","sy":"2.8","c":45},
{"x":11,"y":29,"sx":"1.1","sy":"2.9","c":16},
{"x":11,"y":30,"sx":"1.1","sy":"3.0","c":11},
{"x":11,"y":31,"sx":"1.1","sy":"3.1","c":13},
{"x":11,"y":32,"sx":"1.1","sy":"3.2","c":18},
{"x":11,"y":33,"sx":"1.1","sy":"3.3","c":1},
{"x":11,"y":34,"sx":"1.1","sy":"3.4","c":1},
{"x":11,"y":35,"sx":"1.1","sy":"3.5","c":2},
{"x":11,"y":36,"sx":"1.1","sy":"3.6","c":1},
{"x":11,"y":37,"sx":"1.1","sy":"3.7","c":1},
{"x":11,"y":39,"sx":"1.1","sy":"3.9","c":1},
{"x":11,"y":42,"sx":"1.1","sy":"4.2","c":1},
{"x":11,"y":48,"sx":"1.1","sy":"4.8","c":1},
{"x":11,"y":78,"sx":"1.1","sy":"7.8","c":1},
{"x":12,"y":12,"sx":"1.2","sy":"1.2","c":6},
{"x":12,"y":13,"sx":"1.2","sy":"1.3","c":27},
{"x":12,"y":14,"sx":"1.2","sy":"1.4","c":39},
{"x":12,"y":15,"sx":"1.2","sy":"1.5","c":47},
{"x":12,"y":16,"sx":"1.2","sy":"1.6","c":63},
{"x":12,"y":17,"sx":"1.2","sy":"1.7","c":76},
{"x":12,"y":18,"sx":"1.2","sy":"1.8","c":78},
{"x":12,"y":19,"sx":"1.2","sy":"1.9","c":51},
{"x":12,"y":20,"sx":"1.2","sy":"2.0","c":45},
{"x":12,"y":21,"sx":"1.2","sy":"2.1","c":145},
{"x":12,"y":22,"sx":"1.2","sy":"2.2","c":161},
{"x":12,"y":23,"sx":"1.2","sy":"2.3","c":108},
{"x":12,"y":24,"sx":"1.2","sy":"2.4","c":68},
{"x":12,"y":25,"sx":"1.2","sy":"2.5","c":74},
{"x":12,"y":26,"sx":"1.2","sy":"2.6","c":98},
{"x":12,"y":27,"sx":"1.2","sy":"2.7","c":61},
{"x":12,"y":28,"sx":"1.2","sy":"2.8","c":35},
{"x":12,"y":29,"sx":"1.2","sy":"2.9","c":19},
{"x":12,"y":30,"sx":"1.2","sy":"3.0","c":16},
{"x":12,"y":31,"sx":"1.2","sy":"3.1","c":6},
{"x":12,"y":32,"sx":"1.2","sy":"3.2","c":11},
{"x":12,"y":33,"sx":"1.2","sy":"3.3","c":10},
{"x":12,"y":35,"sx":"1.2","sy":"3.5","c":1},
{"x":12,"y":36,"sx":"1.2","sy":"3.6","c":1},
{"x":12,"y":37,"sx":"1.2","sy":"3.7","c":1},
{"x":12,"y":38,"sx":"1.2","sy":"3.8","c":2},
{"x":12,"y":42,"sx":"1.2","sy":"4.2","c":2},
{"x":13,"y":13,"sx":"1.3","sy":"1.3","c":4},
{"x":13,"y":14,"sx":"1.3","sy":"1.4","c":25},
{"x":13,"y":15,"sx":"1.3","sy":"1.5","c":33},
{"x":13,"y":16,"sx":"1.3","sy":"1.6","c":44},
{"x":13,"y":17,"sx":"1.3","sy":"1.7","c":86},
{"x":13,"y":18,"sx":"1.3","sy":"1.8","c":168},
{"x":13,"y":19,"sx":"1.3","sy":"1.9","c":66},
{"x":13,"y":20,"sx":"1.3","sy":"2.0","c":45},
{"x":13,"y":21,"sx":"1.3","sy":"2.1","c":166},
{"x":13,"y":22,"sx":"1.3","sy":"2.2","c":178},
{"x":13,"y":23,"sx":"1.3","sy":"2.3","c":139},
{"x":13,"y":24,"sx":"1.3","sy":"2.4","c":98},
{"x":13,"y":25,"sx":"1.3","sy":"2.5","c":112},
{"x":13,"y":26,"sx":"1.3","sy":"2.6","c":138},
{"x":13,"y":27,"sx":"1.3","sy":"2.7","c":57},
{"x":13,"y":28,"sx":"1.3","sy":"2.8","c":30},
{"x":13,"y":29,"sx":"1.3","sy":"2.9","c":39},
{"x":13,"y":30,"sx":"1.3","sy":"3.0","c":24},
{"x":13,"y":31,"sx":"1.3","sy":"3.1","c":18},
{"x":13,"y":32,"sx":"1.3","sy":"3.2","c":5},
{"x":13,"y":33,"sx":"1.3","sy":"3.3","c":10},
{"x":13,"y":34,"sx":"1.3","sy":"3.4","c":1},
{"x":13,"y":44,"sx":"1.3","sy":"4.4","c":1},
{"x":13,"y":46,"sx":"1.3","sy":"4.6","c":1},
{"x":13,"y":47,"sx":"1.3","sy":"4.7","c":1},
{"x":13,"y":71,"sx":"1.3","sy":"7.1","c":1},
{"x":14,"y":14,"sx":"1.4","sy":"1.4","c":14},
{"x":14,"y":15,"sx":"1.4","sy":"1.5","c":53},
{"x":14,"y":16,"sx":"1.4","sy":"1.6","c":61},
{"x":14,"y":17,"sx":"1.4","sy":"1.7","c":102},
{"x":14,"y":18,"sx":"1.4","sy":"1.8","c":213},
{"x":14,"y":19,"sx":"1.4","sy":"1.9","c":92},
{"x":14,"y":20,"sx":"1.4","sy":"2.0","c":64},
{"x":14,"y":21,"sx":"1.4","sy":"2.1","c":235},
{"x":14,"y":22,"sx":"1.4","sy":"2.2","c":280},
{"x":14,"y":23,"sx":"1.4","sy":"2.3","c":205},
{"x":14,"y":24,"sx":"1.4","sy":"2.4","c":84},
{"x":14,"y":25,"sx":"1.4","sy":"2.5","c":176},
{"x":14,"y":26,"sx":"1.4","sy":"2.6","c":204},
{"x":14,"y":27,"sx":"1.4","sy":"2.7","c":96},
{"x":14,"y":28,"sx":"1.4","sy":"2.8","c":29},
{"x":14,"y":29,"sx":"1.4","sy":"2.9","c":23},
{"x":14,"y":30,"sx":"1.4","sy":"3.0","c":28},
{"x":14,"y":31,"sx":"1.4","sy":"3.1","c":21},
{"x":14,"y":32,"sx":"1.4","sy":"3.2","c":13},
{"x":14,"y":33,"sx":"1.4","sy":"3.3","c":7},
{"x":14,"y":34,"sx":"1.4","sy":"3.4","c":3},
{"x":14,"y":35,"sx":"1.4","sy":"3.5","c":2},
{"x":14,"y":36,"sx":"1.4","sy":"3.6","c":1},
{"x":14,"y":40,"sx":"1.4","sy":"4.0","c":1},
{"x":14,"y":41,"sx":"1.4","sy":"4.1","c":1},
{"x":14,"y":42,"sx":"1.4","sy":"4.2","c":2},
{"x":14,"y":65,"sx":"1.4","sy":"6.5","c":1},
{"x":15,"y":15,"sx":"1.5","sy":"1.5","c":10},
{"x":15,"y":16,"sx":"1.5","sy":"1.6","c":43},
{"x":15,"y":17,"sx":"1.5","sy":"1.7","c":144},
{"x":15,"y":18,"sx":"1.5","sy":"1.8","c":430},
{"x":15,"y":19,"sx":"1.5","sy":"1.9","c":293},
{"x":15,"y":20,"sx":"1.5","sy":"2.0","c":74},
{"x":15,"y":21,"sx":"1.5","sy":"2.1","c":425},
{"x":15,"y":22,"sx":"1.5","sy":"2.2","c":681},
{"x":15,"y":23,"sx":"1.5","sy":"2.3","c":577},
{"x":15,"y":24,"sx":"1.5","sy":"2.4","c":182},
{"x":15,"y":25,"sx":"1.5","sy":"2.5","c":274},
{"x":15,"y":26,"sx":"1.5","sy":"2.6","c":380},
{"x":15,"y":27,"sx":"1.5","sy":"2.7","c":131},
{"x":15,"y":28,"sx":"1.5","sy":"2.8","c":44},
{"x":15,"y":29,"sx":"1.5","sy":"2.9","c":44},
{"x":15,"y":30,"sx":"1.5","sy":"3.0","c":35},
{"x":15,"y":31,"sx":"1.5","sy":"3.1","c":39},
{"x":15,"y":32,"sx":"1.5","sy":"3.2","c":16},
{"x":15,"y":33,"sx":"1.5","sy":"3.3","c":6},
{"x":15,"y":34,"sx":"1.5","sy":"3.4","c":1},
{"x":15,"y":37,"sx":"1.5","sy":"3.7","c":1},
{"x":15,"y":38,"sx":"1.5","sy":"3.8","c":1},
{"x":15,"y":41,"sx":"1.5","sy":"4.1","c":1},
{"x":15,"y":42,"sx":"1.5","sy":"4.2","c":1},
{"x":15,"y":43,"sx":"1.5","sy":"4.3","c":1},
{"x":15,"y":54,"sx":"1.5","sy":"5.4","c":1},
{"x":16,"y":16,"sx":"1.6","sy":"1.6","c":34},
{"x":16,"y":17,"sx":"1.6","sy":"1.7","c":176},
{"x":16,"y":18,"sx":"1.6","sy":"1.8","c":1790},
{"x":16,"y":19,"sx":"1.6","sy":"1.9","c":1144},
{"x":16,"y":20,"sx":"1.6","sy":"2.0","c":410},
{"x":16,"y":21,"sx":"1.6","sy":"2.1","c":1389},
{"x":16,"y":22,"sx":"1.6","sy":"2.2","c":2650},
{"x":16,"y":23,"sx":"1.6","sy":"2.3","c":2009},
{"x":16,"y":24,"sx":"1.6","sy":"2.4","c":485},
{"x":16,"y":25,"sx":"1.6","sy":"2.5","c":689},
{"x":16,"y":26,"sx":"1.6","sy":"2.6","c":823},
{"x":16,"y":27,"sx":"1.6","sy":"2.7","c":213},
{"x":16,"y":28,"sx":"1.6","sy":"2.8","c":43},
{"x":16,"y":29,"sx":"1.6","sy":"2.9","c":40},
{"x":16,"y":30,"sx":"1.6","sy":"3.0","c":62},
{"x":16,"y":31,"sx":"1.6","sy":"3.1","c":63},
{"x":16,"y":32,"sx":"1.6","sy":"3.2","c":13},
{"x":16,"y":33,"sx":"1.6","sy":"3.3","c":10},
{"x":16,"y":34,"sx":"1.6","sy":"3.4","c":2},
{"x":16,"y":35,"sx":"1.6","sy":"3.5","c":2},
{"x":16,"y":36,"sx":"1.6","sy":"3.6","c":1},
{"x":16,"y":37,"sx":"1.6","sy":"3.7","c":4},
{"x":16,"y":38,"sx":"1.6","sy":"3.8","c":1},
{"x":16,"y":41,"sx":"1.6","sy":"4.1","c":1},
{"x":16,"y":43,"sx":"1.6","sy":"4.3","c":1},
{"x":16,"y":44,"sx":"1.6","sy":"4.4","c":2},
{"x":17,"y":17,"sx":"1.7","sy":"1.7","c":46},
{"x":17,"y":18,"sx":"1.7","sy":"1.8","c":2675},
{"x":17,"y":19,"sx":"1.7","sy":"1.9","c":4572},
{"x":17,"y":20,"sx":"1.7","sy":"2.0","c":556},
{"x":17,"y":21,"sx":"1.7","sy":"2.1","c":3262},
{"x":17,"y":22,"sx":"1.7","sy":"2.2","c":8258},
{"x":17,"y":23,"sx":"1.7","sy":"2.3","c":7971},
{"x":17,"y":24,"sx":"1.7","sy":"2.4","c":1358},
{"x":17,"y":25,"sx":"1.7","sy":"2.5","c":2087},
{"x":17,"y":26,"sx":"1.7","sy":"2.6","c":1665},
{"x":17,"y":27,"sx":"1.7","sy":"2.7","c":392},
{"x":17,"y":28,"sx":"1.7","sy":"2.8","c":63},
{"x":17,"y":29,"sx":"1.7","sy":"2.9","c":41},
{"x":17,"y":30,"sx":"1.7","sy":"3.0","c":99},
{"x":17,"y":31,"sx":"1.7","sy":"3.1","c":81},
{"x":17,"y":32,"sx":"1.7","sy":"3.2","c":22},
{"x":17,"y":33,"sx":"1.7","sy":"3.3","c":16},
{"x":17,"y":34,"sx":"1.7","sy":"3.4","c":1},
{"x":17,"y":35,"sx":"1.7","sy":"3.5","c":1},
{"x":17,"y":36,"sx":"1.7","sy":"3.6","c":4},
{"x":17,"y":37,"sx":"1.7","sy":"3.7","c":3},
{"x":17,"y":40,"sx":"1.7","sy":"4.0","c":1},
{"x":17,"y":41,"sx":"1.7","sy":"4.1","c":1},
{"x":17,"y":43,"sx":"1.7","sy":"4.3","c":1},
{"x":17,"y":45,"sx":"1.7","sy":"4.5","c":1},
{"x":17,"y":67,"sx":"1.7","sy":"6.7","c":1},
{"x":17,"y":74,"sx":"1.7","sy":"7.4","c":1},
{"x":18,"y":18,"sx":"1.8","sy":"1.8","c":493},
{"x":18,"y":19,"sx":"1.8","sy":"1.9","c":3104},
{"x":18,"y":20,"sx":"1.8","sy":"2.0","c":540},
{"x":18,"y":21,"sx":"1.8","sy":"2.1","c":3641},
{"x":18,"y":22,"sx":"1.8","sy":"2.2","c":14499},
{"x":18,"y":23,"sx":"1.8","sy":"2.3","c":18019},
{"x":18,"y":24,"sx":"1.8","sy":"2.4","c":4743},
{"x":18,"y":25,"sx":"1.8","sy":"2.5","c":4672},
{"x":18,"y":26,"sx":"1.8","sy":"2.6","c":4342},
{"x":18,"y":27,"sx":"1.8","sy":"2.7","c":1085},
{"x":18,"y":28,"sx":"1.8","sy":"2.8","c":121},
{"x":18,"y":29,"sx":"1.8","sy":"2.9","c":84},
{"x":18,"y":30,"sx":"1.8","sy":"3.0","c":154},
{"x":18,"y":31,"sx":"1.8","sy":"3.1","c":129},
{"x":18,"y":32,"sx":"1.8","sy":"3.2","c":23},
{"x":18,"y":33,"sx":"1.8","sy":"3.3","c":7},
{"x":18,"y":34,"sx":"1.8","sy":"3.4","c":5},
{"x":18,"y":35,"sx":"1.8","sy":"3.5","c":5},
{"x":18,"y":36,"sx":"1.8","sy":"3.6","c":3},
{"x":18,"y":37,"sx":"1.8","sy":"3.7","c":2},
{"x":18,"y":38,"sx":"1.8","sy":"3.8","c":1},
{"x":18,"y":41,"sx":"1.8","sy":"4.1","c":1},
{"x":18,"y":42,"sx":"1.8","sy":"4.2","c":1},
{"x":18,"y":51,"sx":"1.8","sy":"5.1","c":2},
{"x":19,"y":19,"sx":"1.9","sy":"1.9","c":132},
{"x":19,"y":20,"sx":"1.9","sy":"2.0","c":116},
{"x":19,"y":21,"sx":"1.9","sy":"2.1","c":3273},
{"x":19,"y":22,"sx":"1.9","sy":"2.2","c":15468},
{"x":19,"y":23,"sx":"1.9","sy":"2.3","c":23962},
{"x":19,"y":24,"sx":"1.9","sy":"2.4","c":12429},
{"x":19,"y":25,"sx":"1.9","sy":"2.5","c":7532},
{"x":19,"y":26,"sx":"1.9","sy":"2.6","c":7896},
{"x":19,"y":27,"sx":"1.9","sy":"2.7","c":2421},
{"x":19,"y":28,"sx":"1.9","sy":"2.8","c":314},
{"x":19,"y":29,"sx":"1.9","sy":"2.9","c":156},
{"x":19,"y":30,"sx":"1.9","sy":"3.0","c":319},
{"x":19,"y":31,"sx":"1.9","sy":"3.1","c":178},
{"x":19,"y":32,"sx":"1.9","sy":"3.2","c":35},
{"x":19,"y":33,"sx":"1.9","sy":"3.3","c":11},
{"x":19,"y":34,"sx":"1.9","sy":"3.4","c":8},
{"x":19,"y":35,"sx":"1.9","sy":"3.5","c":5},
{"x":19,"y":36,"sx":"1.9","sy":"3.6","c":3},
{"x":19,"y":37,"sx":"1.9","sy":"3.7","c":2},
{"x":19,"y":38,"sx":"1.9","sy":"3.8","c":1},
{"x":19,"y":39,"sx":"1.9","sy":"3.9","c":1},
{"x":19,"y":45,"sx":"1.9","sy":"4.5","c":1},
{"x":19,"y":57,"sx":"1.9","sy":"5.7","c":1},
{"x":19,"y":96,"sx":"1.9","sy":"9.6","c":1},
{"x":20,"y":20,"sx":"2.0","sy":"2.0","c":48},
{"x":20,"y":21,"sx":"2.0","sy":"2.1","c":1854},
{"x":20,"y":22,"sx":"2.0","sy":"2.2","c":10662},
{"x":20,"y":23,"sx":"2.0","sy":"2.3","c":21222},
{"x":20,"y":24,"sx":"2.0","sy":"2.4","c":13719},
{"x":20,"y":25,"sx":"2.0","sy":"2.5","c":11795},
{"x":20,"y":26,"sx":"2.0","sy":"2.6","c":10917},
{"x":20,"y":27,"sx":"2.0","sy":"2.7","c":3541},
{"x":20,"y":28,"sx":"2.0","sy":"2.8","c":538},
{"x":20,"y":29,"sx":"2.0","sy":"2.9","c":402},
{"x":20,"y":30,"sx":"2.0","sy":"3.0","c":762},
{"x":20,"y":31,"sx":"2.0","sy":"3.1","c":352},
{"x":20,"y":32,"sx":"2.0","sy":"3.2","c":68},
{"x":20,"y":33,"sx":"2.0","sy":"3.3","c":16},
{"x":20,"y":34,"sx":"2.0","sy":"3.4","c":4},
{"x":20,"y":35,"sx":"2.0","sy":"3.5","c":3},
{"x":20,"y":36,"sx":"2.0","sy":"3.6","c":3},
{"x":20,"y":37,"sx":"2.0","sy":"3.7","c":2},
{"x":20,"y":38,"sx":"2.0","sy":"3.8","c":2},
{"x":20,"y":39,"sx":"2.0","sy":"3.9","c":1},
{"x":20,"y":40,"sx":"2.0","sy":"4.0","c":2},
{"x":20,"y":41,"sx":"2.0","sy":"4.1","c":1},
{"x":20,"y":48,"sx":"2.0","sy":"4.8","c":1},
{"x":20,"y":51,"sx":"2.0","sy":"5.1","c":1},
{"x":20,"y":81,"sx":"2.0","sy":"8.1","c":1},
{"x":21,"y":21,"sx":"2.1","sy":"2.1","c":358},
{"x":21,"y":22,"sx":"2.1","sy":"2.2","c":4152},
{"x":21,"y":23,"sx":"2.1","sy":"2.3","c":10724},
{"x":21,"y":24,"sx":"2.1","sy":"2.4","c":10189},
{"x":21,"y":25,"sx":"2.1","sy":"2.5","c":13483},
{"x":21,"y":26,"sx":"2.1","sy":"2.6","c":14556},
{"x":21,"y":27,"sx":"2.1","sy":"2.7","c":7019},
{"x":21,"y":28,"sx":"2.1","sy":"2.8","c":1004},
{"x":21,"y":29,"sx":"2.1","sy":"2.9","c":607},
{"x":21,"y":30,"sx":"2.1","sy":"3.0","c":1551},
{"x":21,"y":31,"sx":"2.1","sy":"3.1","c":939},
{"x":21,"y":32,"sx":"2.1","sy":"3.2","c":73},
{"x":21,"y":33,"sx":"2.1","sy":"3.3","c":24},
{"x":21,"y":34,"sx":"2.1","sy":"3.4","c":5},
{"x":21,"y":36,"sx":"2.1","sy":"3.6","c":4},
{"x":21,"y":37,"sx":"2.1","sy":"3.7","c":3},
{"x":21,"y":38,"sx":"2.1","sy":"3.8","c":3},
{"x":21,"y":39,"sx":"2.1","sy":"3.9","c":3},
{"x":21,"y":40,"sx":"2.1","sy":"4.0","c":1},
{"x":21,"y":41,"sx":"2.1","sy":"4.1","c":1},
{"x":21,"y":42,"sx":"2.1","sy":"4.2","c":1},
{"x":21,"y":43,"sx":"2.1","sy":"4.3","c":1},
{"x":21,"y":49,"sx":"2.1","sy":"4.9","c":1},
{"x":21,"y":61,"sx":"2.1","sy":"6.1","c":2},
{"x":21,"y":93,"sx":"2.1","sy":"9.3","c":1},
{"x":22,"y":22,"sx":"2.2","sy":"2.2","c":390},
{"x":22,"y":23,"sx":"2.2","sy":"2.3","c":4128},
{"x":22,"y":24,"sx":"2.2","sy":"2.4","c":5419},
{"x":22,"y":25,"sx":"2.2","sy":"2.5","c":12605},
{"x":22,"y":26,"sx":"2.2","sy":"2.6","c":15222},
{"x":22,"y":27,"sx":"2.2","sy":"2.7","c":9412},
{"x":22,"y":28,"sx":"2.2","sy":"2.8","c":1479},
{"x":22,"y":29,"sx":"2.2","sy":"2.9","c":1215},
{"x":22,"y":30,"sx":"2.2","sy":"3.0","c":2634},
{"x":22,"y":31,"sx":"2.2","sy":"3.1","c":2074},
{"x":22,"y":32,"sx":"2.2","sy":"3.2","c":248},
{"x":22,"y":33,"sx":"2.2","sy":"3.3","c":36},
{"x":22,"y":34,"sx":"2.2","sy":"3.4","c":10},
{"x":22,"y":35,"sx":"2.2","sy":"3.5","c":3},
{"x":22,"y":36,"sx":"2.2","sy":"3.6","c":3},
{"x":22,"y":38,"sx":"2.2","sy":"3.8","c":2},
{"x":22,"y":39,"sx":"2.2","sy":"3.9","c":1},
{"x":22,"y":42,"sx":"2.2","sy":"4.2","c":1},
{"x":22,"y":45,"sx":"2.2","sy":"4.5","c":1},
{"x":22,"y":48,"sx":"2.2","sy":"4.8","c":1},
{"x":22,"y":66,"sx":"2.2","sy":"6.6","c":1},
{"x":22,"y":72,"sx":"2.2","sy":"7.2","c":1},
{"x":23,"y":23,"sx":"2.3","sy":"2.3","c":293},
{"x":23,"y":24,"sx":"2.3","sy":"2.4","c":1576},
{"x":23,"y":25,"sx":"2.3","sy":"2.5","c":8096},
{"x":23,"y":26,"sx":"2.3","sy":"2.6","c":13644},
{"x":23,"y":27,"sx":"2.3","sy":"2.7","c":11272},
{"x":23,"y":28,"sx":"2.3","sy":"2.8","c":2148},
{"x":23,"y":29,"sx":"2.3","sy":"2.9","c":1553},
{"x":23,"y":30,"sx":"2.3","sy":"3.0","c":3824},
{"x":23,"y":31,"sx":"2.3","sy":"3.1","c":3845},
{"x":23,"y":32,"sx":"2.3","sy":"3.2","c":382},
{"x":23,"y":33,"sx":"2.3","sy":"3.3","c":31},
{"x":23,"y":34,"sx":"2.3","sy":"3.4","c":9},
{"x":23,"y":35,"sx":"2.3","sy":"3.5","c":7},
{"x":23,"y":36,"sx":"2.3","sy":"3.6","c":3},
{"x":23,"y":37,"sx":"2.3","sy":"3.7","c":6},
{"x":23,"y":38,"sx":"2.3","sy":"3.8","c":4},
{"x":23,"y":39,"sx":"2.3","sy":"3.9","c":6},
{"x":23,"y":40,"sx":"2.3","sy":"4.0","c":2},
{"x":23,"y":41,"sx":"2.3","sy":"4.1","c":1},
{"x":23,"y":43,"sx":"2.3","sy":"4.3","c":1},
{"x":23,"y":45,"sx":"2.3","sy":"4.5","c":1},
{"x":23,"y":48,"sx":"2.3","sy":"4.8","c":1},
{"x":23,"y":56,"sx":"2.3","sy":"5.6","c":1},
{"x":23,"y":97,"sx":"2.3","sy":"9.7","c":1},
{"x":24,"y":24,"sx":"2.4","sy":"2.4","c":170},
{"x":24,"y":25,"sx":"2.4","sy":"2.5","c":4318},
{"x":24,"y":26,"sx":"2.4","sy":"2.6","c":10460},
{"x":24,"y":27,"sx":"2.4","sy":"2.7","c":11711},
{"x":24,"y":28,"sx":"2.4","sy":"2.8","c":3222},
{"x":24,"y":29,"sx":"2.4","sy":"2.9","c":2301},
{"x":24,"y":30,"sx":"2.4","sy":"3.0","c":5323},
{"x":24,"y":31,"sx":"2.4","sy":"3.1","c":7001},
{"x":24,"y":32,"sx":"2.4","sy":"3.2","c":553},
{"x":24,"y":33,"sx":"2.4","sy":"3.3","c":39},
{"x":24,"y":34,"sx":"2.4","sy":"3.4","c":10},
{"x":24,"y":35,"sx":"2.4","sy":"3.5","c":11},
{"x":24,"y":36,"sx":"2.4","sy":"3.6","c":1},
{"x":24,"y":37,"sx":"2.4","sy":"3.7","c":1},
{"x":24,"y":38,"sx":"2.4","sy":"3.8","c":1},
{"x":24,"y":39,"sx":"2.4","sy":"3.9","c":2},
{"x":24,"y":42,"sx":"2.4","sy":"4.2","c":1},
{"x":24,"y":43,"sx":"2.4","sy":"4.3","c":1},
{"x":24,"y":44,"sx":"2.4","sy":"4.4","c":1},
{"x":24,"y":45,"sx":"2.4","sy":"4.5","c":1},
{"x":24,"y":46,"sx":"2.4","sy":"4.6","c":1},
{"x":24,"y":47,"sx":"2.4","sy":"4.7","c":1},
{"x":24,"y":48,"sx":"2.4","sy":"4.8","c":1},
{"x":24,"y":58,"sx":"2.4","sy":"5.8","c":1},
{"x":24,"y":91,"sx":"2.4","sy":"9.1","c":1},
{"x":25,"y":25,"sx":"2.5","sy":"2.5","c":738},
{"x":25,"y":26,"sx":"2.5","sy":"2.6","c":7095},
{"x":25,"y":27,"sx":"2.5","sy":"2.7","c":13153},
{"x":25,"y":28,"sx":"2.5","sy":"2.8","c":4238},
{"x":25,"y":29,"sx":"2.5","sy":"2.9","c":3500},
{"x":25,"y":30,"sx":"2.5","sy":"3.0","c":7685},
{"x":25,"y":31,"sx":"2.5","sy":"3.1","c":9221},
{"x":25,"y":32,"sx":"2.5","sy":"3.2","c":807},
{"x":25,"y":33,"sx":"2.5","sy":"3.3","c":31},
{"x":25,"y":34,"sx":"2.5","sy":"3.4","c":11},
{"x":25,"y":35,"sx":"2.5","sy":"3.5","c":1},
{"x":25,"y":36,"sx":"2.5","sy":"3.6","c":1},
{"x":25,"y":37,"sx":"2.5","sy":"3.7","c":1},
{"x":25,"y":38,"sx":"2.5","sy":"3.8","c":4},
{"x":25,"y":39,"sx":"2.5","sy":"3.9","c":31},
{"x":25,"y":40,"sx":"2.5","sy":"4.0","c":1},
{"x":25,"y":43,"sx":"2.5","sy":"4.3","c":1},
{"x":25,"y":44,"sx":"2.5","sy":"4.4","c":1},
{"x":25,"y":49,"sx":"2.5","sy":"4.9","c":1},
{"x":25,"y":50,"sx":"2.5","sy":"5.0","c":2},
{"x":26,"y":26,"sx":"2.6","sy":"2.6","c":1296},
{"x":26,"y":27,"sx":"2.6","sy":"2.7","c":8864},
{"x":26,"y":28,"sx":"2.6","sy":"2.8","c":6161},
{"x":26,"y":29,"sx":"2.6","sy":"2.9","c":6504},
{"x":26,"y":30,"sx":"2.6","sy":"3.0","c":10546},
{"x":26,"y":31,"sx":"2.6","sy":"3.1","c":10788},
{"x":26,"y":32,"sx":"2.6","sy":"3.2","c":1416},
{"x":26,"y":33,"sx":"2.6","sy":"3.3","c":38},
{"x":26,"y":34,"sx":"2.6","sy":"3.4","c":15},
{"x":26,"y":35,"sx":"2.6","sy":"3.5","c":7},
{"x":26,"y":36,"sx":"2.6","sy":"3.6","c":1},
{"x":26,"y":38,"sx":"2.6","sy":"3.8","c":57},
{"x":26,"y":39,"sx":"2.6","sy":"3.9","c":94},
{"x":26,"y":40,"sx":"2.6","sy":"4.0","c":1},
{"x":26,"y":44,"sx":"2.6","sy":"4.4","c":1},
{"x":26,"y":45,"sx":"2.6","sy":"4.5","c":2},
{"x":26,"y":47,"sx":"2.6","sy":"4.7","c":1},
{"x":26,"y":59,"sx":"2.6","sy":"5.9","c":1},
{"x":27,"y":27,"sx":"2.7","sy":"2.7","c":1907},
{"x":27,"y":28,"sx":"2.7","sy":"2.8","c":3786},
{"x":27,"y":29,"sx":"2.7","sy":"2.9","c":6786},
{"x":27,"y":30,"sx":"2.7","sy":"3.0","c":11916},
{"x":27,"y":31,"sx":"2.7","sy":"3.1","c":11035},
{"x":27,"y":32,"sx":"2.7","sy":"3.2","c":2210},
{"x":27,"y":33,"sx":"2.7","sy":"3.3","c":67},
{"x":27,"y":34,"sx":"2.7","sy":"3.4","c":20},
{"x":27,"y":35,"sx":"2.7","sy":"3.5","c":3},
{"x":27,"y":36,"sx":"2.7","sy":"3.6","c":3},
{"x":27,"y":37,"sx":"2.7","sy":"3.7","c":2},
{"x":27,"y":38,"sx":"2.7","sy":"3.8","c":58},
{"x":27,"y":39,"sx":"2.7","sy":"3.9","c":214},
{"x":27,"y":40,"sx":"2.7","sy":"4.0","c":3},
{"x":27,"y":42,"sx":"2.7","sy":"4.2","c":1},
{"x":27,"y":43,"sx":"2.7","sy":"4.3","c":2},
{"x":27,"y":44,"sx":"2.7","sy":"4.4","c":2},
{"x":27,"y":45,"sx":"2.7","sy":"4.5","c":1},
{"x":27,"y":47,"sx":"2.7","sy":"4.7","c":1},
{"x":27,"y":49,"sx":"2.7","sy":"4.9","c":2},
{"x":27,"y":55,"sx":"2.7","sy":"5.5","c":1},
{"x":27,"y":57,"sx":"2.7","sy":"5.7","c":1},
{"x":27,"y":62,"sx":"2.7","sy":"6.2","c":1},
{"x":28,"y":28,"sx":"2.8","sy":"2.8","c":1045},
{"x":28,"y":29,"sx":"2.8","sy":"2.9","c":4334},
{"x":28,"y":30,"sx":"2.8","sy":"3.0","c":9934},
{"x":28,"y":31,"sx":"2.8","sy":"3.1","c":11069},
{"x":28,"y":32,"sx":"2.8","sy":"3.2","c":2582},
{"x":28,"y":33,"sx":"2.8","sy":"3.3","c":111},
{"x":28,"y":34,"sx":"2.8","sy":"3.4","c":68},
{"x":28,"y":35,"sx":"2.8","sy":"3.5","c":37},
{"x":28,"y":36,"sx":"2.8","sy":"3.6","c":23},
{"x":28,"y":37,"sx":"2.8","sy":"3.7","c":24},
{"x":28,"y":38,"sx":"2.8","sy":"3.8","c":71},
{"x":28,"y":39,"sx":"2.8","sy":"3.9","c":371},
{"x":28,"y":40,"sx":"2.8","sy":"4.0","c":24},
{"x":28,"y":41,"sx":"2.8","sy":"4.1","c":18},
{"x":28,"y":42,"sx":"2.8","sy":"4.2","c":5},
{"x":28,"y":43,"sx":"2.8","sy":"4.3","c":1},
{"x":28,"y":44,"sx":"2.8","sy":"4.4","c":1},
{"x":28,"y":50,"sx":"2.8","sy":"5.0","c":1},
{"x":28,"y":52,"sx":"2.8","sy":"5.2","c":2},
{"x":28,"y":55,"sx":"2.8","sy":"5.5","c":1},
{"x":29,"y":29,"sx":"2.9","sy":"2.9","c":776},
{"x":29,"y":30,"sx":"2.9","sy":"3.0","c":5593},
{"x":29,"y":31,"sx":"2.9","sy":"3.1","c":9497},
{"x":29,"y":32,"sx":"2.9","sy":"3.2","c":2279},
{"x":29,"y":33,"sx":"2.9","sy":"3.3","c":141},
{"x":29,"y":34,"sx":"2.9","sy":"3.4","c":109},
{"x":29,"y":35,"sx":"2.9","sy":"3.5","c":21},
{"x":29,"y":36,"sx":"2.9","sy":"3.6","c":17},
{"x":29,"y":37,"sx":"2.9","sy":"3.7","c":14},
{"x":29,"y":38,"sx":"2.9","sy":"3.8","c":86},
{"x":29,"y":39,"sx":"2.9","sy":"3.9","c":430},
{"x":29,"y":40,"sx":"2.9","sy":"4.0","c":41},
{"x":29,"y":41,"sx":"2.9","sy":"4.1","c":3},
{"x":29,"y":42,"sx":"2.9","sy":"4.2","c":2},
{"x":29,"y":48,"sx":"2.9","sy":"4.8","c":1},
{"x":29,"y":56,"sx":"2.9","sy":"5.6","c":1},
{"x":29,"y":63,"sx":"2.9","sy":"6.3","c":1},
{"x":29,"y":73,"sx":"2.9","sy":"7.3","c":1},
{"x":29,"y":79,"sx":"2.9","sy":"7.9","c":1},
{"x":30,"y":30,"sx":"3.0","sy":"3.0","c":923},
{"x":30,"y":31,"sx":"3.0","sy":"3.1","c":4896},
{"x":30,"y":32,"sx":"3.0","sy":"3.2","c":1854},
{"x":30,"y":33,"sx":"3.0","sy":"3.3","c":152},
{"x":30,"y":34,"sx":"3.0","sy":"3.4","c":201},
{"x":30,"y":35,"sx":"3.0","sy":"3.5","c":8},
{"x":30,"y":36,"sx":"3.0","sy":"3.6","c":2},
{"x":30,"y":37,"sx":"3.0","sy":"3.7","c":3},
{"x":30,"y":38,"sx":"3.0","sy":"3.8","c":98},
{"x":30,"y":39,"sx":"3.0","sy":"3.9","c":455},
{"x":30,"y":40,"sx":"3.0","sy":"4.0","c":53},
{"x":30,"y":41,"sx":"3.0","sy":"4.1","c":1},
{"x":30,"y":42,"sx":"3.0","sy":"4.2","c":3},
{"x":30,"y":44,"sx":"3.0","sy":"4.4","c":1},
{"x":30,"y":47,"sx":"3.0","sy":"4.7","c":1},
{"x":30,"y":52,"sx":"3.0","sy":"5.2","c":1},
{"x":30,"y":53,"sx":"3.0","sy":"5.3","c":1},
{"x":30,"y":57,"sx":"3.0","sy":"5.7","c":1},
{"x":30,"y":58,"sx":"3.0","sy":"5.8","c":3},
{"x":30,"y":59,"sx":"3.0","sy":"5.9","c":2},
{"x":30,"y":68,"sx":"3.0","sy":"6.8","c":1},
{"x":30,"y":70,"sx":"3.0","sy":"7.0","c":1},
{"x":31,"y":31,"sx":"3.1","sy":"3.1","c":617},
{"x":31,"y":32,"sx":"3.1","sy":"3.2","c":960},
{"x":31,"y":33,"sx":"3.1","sy":"3.3","c":186},
{"x":31,"y":34,"sx":"3.1","sy":"3.4","c":233},
{"x":31,"y":35,"sx":"3.1","sy":"3.5","c":56},
{"x":31,"y":36,"sx":"3.1","sy":"3.6","c":2},
{"x":31,"y":37,"sx":"3.1","sy":"3.7","c":1},
{"x":31,"y":38,"sx":"3.1","sy":"3.8","c":88},
{"x":31,"y":39,"sx":"3.1","sy":"3.9","c":417},
{"x":31,"y":40,"sx":"3.1","sy":"4.0","c":48},
{"x":31,"y":41,"sx":"3.1","sy":"4.1","c":1},
{"x":31,"y":42,"sx":"3.1","sy":"4.2","c":1},
{"x":31,"y":46,"sx":"3.1","sy":"4.6","c":1},
{"x":31,"y":51,"sx":"3.1","sy":"5.1","c":1},
{"x":31,"y":60,"sx":"3.1","sy":"6.0","c":1},
{"x":31,"y":61,"sx":"3.1","sy":"6.1","c":1},
{"x":31,"y":84,"sx":"3.1","sy":"8.4","c":1},
{"x":32,"y":32,"sx":"3.2","sy":"3.2","c":88},
{"x":32,"y":33,"sx":"3.2","sy":"3.3","c":131},
{"x":32,"y":34,"sx":"3.2","sy":"3.4","c":207},
{"x":32,"y":35,"sx":"3.2","sy":"3.5","c":94},
{"x":32,"y":36,"sx":"3.2","sy":"3.6","c":6},
{"x":32,"y":38,"sx":"3.2","sy":"3.8","c":57},
{"x":32,"y":39,"sx":"3.2","sy":"3.9","c":379},
{"x":32,"y":40,"sx":"3.2","sy":"4.0","c":42},
{"x":32,"y":41,"sx":"3.2","sy":"4.1","c":1},
{"x":32,"y":42,"sx":"3.2","sy":"4.2","c":1},
{"x":32,"y":44,"sx":"3.2","sy":"4.4","c":1},
{"x":32,"y":47,"sx":"3.2","sy":"4.7","c":1},
{"x":32,"y":52,"sx":"3.2","sy":"5.2","c":1},
{"x":32,"y":53,"sx":"3.2","sy":"5.3","c":1},
{"x":32,"y":54,"sx":"3.2","sy":"5.4","c":1},
{"x":32,"y":59,"sx":"3.2","sy":"5.9","c":1},
{"x":32,"y":66,"sx":"3.2","sy":"6.6","c":1},
{"x":33,"y":33,"sx":"3.3","sy":"3.3","c":41},
{"x":33,"y":34,"sx":"3.3","sy":"3.4","c":156},
{"x":33,"y":35,"sx":"3.3","sy":"3.5","c":63},
{"x":33,"y":36,"sx":"3.3","sy":"3.6","c":6},
{"x":33,"y":37,"sx":"3.3","sy":"3.7","c":5},
{"x":33,"y":38,"sx":"3.3","sy":"3.8","c":34},
{"x":33,"y":39,"sx":"3.3","sy":"3.9","c":358},
{"x":33,"y":40,"sx":"3.3","sy":"4.0","c":40},
{"x":33,"y":41,"sx":"3.3","sy":"4.1","c":3},
{"x":33,"y":42,"sx":"3.3","sy":"4.2","c":1},
{"x":33,"y":43,"sx":"3.3","sy":"4.3","c":1},
{"x":33,"y":44,"sx":"3.3","sy":"4.4","c":1},
{"x":33,"y":48,"sx":"3.3","sy":"4.8","c":1},
{"x":33,"y":54,"sx":"3.3","sy":"5.4","c":1},
{"x":33,"y":56,"sx":"3.3","sy":"5.6","c":2},
{"x":33,"y":63,"sx":"3.3","sy":"6.3","c":1},
{"x":33,"y":66,"sx":"3.3","sy":"6.6","c":1},
{"x":33,"y":71,"sx":"3.3","sy":"7.1","c":1},
{"x":34,"y":34,"sx":"3.4","sy":"3.4","c":22},
{"x":34,"y":35,"sx":"3.4","sy":"3.5","c":40},
{"x":34,"y":36,"sx":"3.4","sy":"3.6","c":4},
{"x":34,"y":37,"sx":"3.4","sy":"3.7","c":2},
{"x":34,"y":38,"sx":"3.4","sy":"3.8","c":37},
{"x":34,"y":39,"sx":"3.4","sy":"3.9","c":271},
{"x":34,"y":40,"sx":"3.4","sy":"4.0","c":21},
{"x":34,"y":42,"sx":"3.4","sy":"4.2","c":1},
{"x":34,"y":44,"sx":"3.4","sy":"4.4","c":2},
{"x":34,"y":48,"sx":"3.4","sy":"4.8","c":1},
{"x":34,"y":49,"sx":"3.4","sy":"4.9","c":18},
{"x":34,"y":50,"sx":"3.4","sy":"5.0","c":19},
{"x":34,"y":54,"sx":"3.4","sy":"5.4","c":1},
{"x":34,"y":68,"sx":"3.4","sy":"6.8","c":1},
{"x":35,"y":35,"sx":"3.5","sy":"3.5","c":2},
{"x":35,"y":36,"sx":"3.5","sy":"3.6","c":4},
{"x":35,"y":37,"sx":"3.5","sy":"3.7","c":1},
{"x":35,"y":38,"sx":"3.5","sy":"3.8","c":27},
{"x":35,"y":39,"sx":"3.5","sy":"3.9","c":150},
{"x":35,"y":40,"sx":"3.5","sy":"4.0","c":28},
{"x":35,"y":46,"sx":"3.5","sy":"4.6","c":1},
{"x":35,"y":47,"sx":"3.5","sy":"4.7","c":2},
{"x":35,"y":48,"sx":"3.5","sy":"4.8","c":1},
{"x":35,"y":49,"sx":"3.5","sy":"4.9","c":24},
{"x":35,"y":50,"sx":"3.5","sy":"5.0","c":17},
{"x":35,"y":51,"sx":"3.5","sy":"5.1","c":15},
{"x":35,"y":52,"sx":"3.5","sy":"5.2","c":1},
{"x":35,"y":69,"sx":"3.5","sy":"6.9","c":1},
{"x":35,"y":81,"sx":"3.5","sy":"8.1","c":2},
{"x":36,"y":36,"sx":"3.6","sy":"3.6","c":2},
{"x":36,"y":38,"sx":"3.6","sy":"3.8","c":8},
{"x":36,"y":39,"sx":"3.6","sy":"3.9","c":79},
{"x":36,"y":40,"sx":"3.6","sy":"4.0","c":13},
{"x":36,"y":41,"sx":"3.6","sy":"4.1","c":2},
{"x":36,"y":48,"sx":"3.6","sy":"4.8","c":2},
{"x":36,"y":49,"sx":"3.6","sy":"4.9","c":8},
{"x":36,"y":50,"sx":"3.6","sy":"5.0","c":9},
{"x":36,"y":51,"sx":"3.6","sy":"5.1","c":9},
{"x":36,"y":52,"sx":"3.6","sy":"5.2","c":9},
{"x":36,"y":53,"sx":"3.6","sy":"5.3","c":1},
{"x":36,"y":66,"sx":"3.6","sy":"6.6","c":1},
{"x":37,"y":38,"sx":"3.7","sy":"3.8","c":11},
{"x":37,"y":39,"sx":"3.7","sy":"3.9","c":43},
{"x":37,"y":40,"sx":"3.7","sy":"4.0","c":5},
{"x":37,"y":42,"sx":"3.7","sy":"4.2","c":1},
{"x":37,"y":46,"sx":"3.7","sy":"4.6","c":1},
{"x":37,"y":48,"sx":"3.7","sy":"4.8","c":3},
{"x":37,"y":49,"sx":"3.7","sy":"4.9","c":10},
{"x":37,"y":50,"sx":"3.7","sy":"5.0","c":8},
{"x":37,"y":51,"sx":"3.7","sy":"5.1","c":12},
{"x":37,"y":52,"sx":"3.7","sy":"5.2","c":17},
{"x":37,"y":63,"sx":"3.7","sy":"6.3","c":1},
{"x":37,"y":74,"sx":"3.7","sy":"7.4","c":2},
{"x":37,"y":92,"sx":"3.7","sy":"9.2","c":2},
{"x":37,"y":99,"sx":"3.7","sy":"9.9","c":1},
{"x":38,"y":38,"sx":"3.8","sy":"3.8","c":2},
{"x":38,"y":39,"sx":"3.8","sy":"3.9","c":20},
{"x":38,"y":40,"sx":"3.8","sy":"4.0","c":3},
{"x":38,"y":41,"sx":"3.8","sy":"4.1","c":4},
{"x":38,"y":42,"sx":"3.8","sy":"4.2","c":1},
{"x":38,"y":44,"sx":"3.8","sy":"4.4","c":1},
{"x":38,"y":45,"sx":"3.8","sy":"4.5","c":1},
{"x":38,"y":46,"sx":"3.8","sy":"4.6","c":2},
{"x":38,"y":48,"sx":"3.8","sy":"4.8","c":1},
{"x":38,"y":49,"sx":"3.8","sy":"4.9","c":10},
{"x":38,"y":50,"sx":"3.8","sy":"5.0","c":9},
{"x":38,"y":51,"sx":"3.8","sy":"5.1","c":15},
{"x":38,"y":52,"sx":"3.8","sy":"5.2","c":6},
{"x":38,"y":53,"sx":"3.8","sy":"5.3","c":1},
{"x":38,"y":62,"sx":"3.8","sy":"6.2","c":2},
{"x":38,"y":66,"sx":"3.8","sy":"6.6","c":1},
{"x":38,"y":93,"sx":"3.8","sy":"9.3","c":1},
{"x":39,"y":39,"sx":"3.9","sy":"3.9","c":4},
{"x":39,"y":42,"sx":"3.9","sy":"4.2","c":2},
{"x":39,"y":43,"sx":"3.9","sy":"4.3","c":1},
{"x":39,"y":45,"sx":"3.9","sy":"4.5","c":1},
{"x":39,"y":46,"sx":"3.9","sy":"4.6","c":2},
{"x":39,"y":47,"sx":"3.9","sy":"4.7","c":3},
{"x":39,"y":48,"sx":"3.9","sy":"4.8","c":3},
{"x":39,"y":49,"sx":"3.9","sy":"4.9","c":13},
{"x":39,"y":50,"sx":"3.9","sy":"5.0","c":2},
{"x":39,"y":51,"sx":"3.9","sy":"5.1","c":8},
{"x":39,"y":52,"sx":"3.9","sy":"5.2","c":5},
{"x":39,"y":53,"sx":"3.9","sy":"5.3","c":2},
{"x":39,"y":64,"sx":"3.9","sy":"6.4","c":2},
{"x":40,"y":42,"sx":"4.0","sy":"4.2","c":1},
{"x":40,"y":43,"sx":"4.0","sy":"4.3","c":1},
{"x":40,"y":47,"sx":"4.0","sy":"4.7","c":1},
{"x":40,"y":48,"sx":"4.0","sy":"4.8","c":3},
{"x":40,"y":49,"sx":"4.0","sy":"4.9","c":11},
{"x":40,"y":50,"sx":"4.0","sy":"5.0","c":7},
{"x":40,"y":51,"sx":"4.0","sy":"5.1","c":9},
{"x":40,"y":52,"sx":"4.0","sy":"5.2","c":9},
{"x":40,"y":53,"sx":"4.0","sy":"5.3","c":1},
{"x":40,"y":58,"sx":"4.0","sy":"5.8","c":1},
{"x":40,"y":76,"sx":"4.0","sy":"7.6","c":1},
{"x":41,"y":41,"sx":"4.1","sy":"4.1","c":1},
{"x":41,"y":43,"sx":"4.1","sy":"4.3","c":1},
{"x":41,"y":46,"sx":"4.1","sy":"4.6","c":3},
{"x":41,"y":48,"sx":"4.1","sy":"4.8","c":5},
{"x":41,"y":49,"sx":"4.1","sy":"4.9","c":4},
{"x":41,"y":50,"sx":"4.1","sy":"5.0","c":4},
{"x":41,"y":51,"sx":"4.1","sy":"5.1","c":19},
{"x":41,"y":52,"sx":"4.1","sy":"5.2","c":23},
{"x":41,"y":54,"sx":"4.1","sy":"5.4","c":1},
{"x":41,"y":55,"sx":"4.1","sy":"5.5","c":1},
{"x":41,"y":57,"sx":"4.1","sy":"5.7","c":1},
{"x":41,"y":72,"sx":"4.1","sy":"7.2","c":1},
{"x":42,"y":43,"sx":"4.2","sy":"4.3","c":2},
{"x":42,"y":45,"sx":"4.2","sy":"4.5","c":1},
{"x":42,"y":47,"sx":"4.2","sy":"4.7","c":1},
{"x":42,"y":49,"sx":"4.2","sy":"4.9","c":5},
{"x":42,"y":50,"sx":"4.2","sy":"5.0","c":6},
{"x":42,"y":51,"sx":"4.2","sy":"5.1","c":32},
{"x":42,"y":52,"sx":"4.2","sy":"5.2","c":30},
{"x":42,"y":53,"sx":"4.2","sy":"5.3","c":4},
{"x":42,"y":58,"sx":"4.2","sy":"5.8","c":1},
{"x":42,"y":60,"sx":"4.2","sy":"6.0","c":2},
{"x":42,"y":63,"sx":"4.2","sy":"6.3","c":1},
{"x":43,"y":48,"sx":"4.3","sy":"4.8","c":1},
{"x":43,"y":49,"sx":"4.3","sy":"4.9","c":2},
{"x":43,"y":50,"sx":"4.3","sy":"5.0","c":6},
{"x":43,"y":51,"sx":"4.3","sy":"5.1","c":65},
{"x":43,"y":52,"sx":"4.3","sy":"5.2","c":70},
{"x":43,"y":53,"sx":"4.3","sy":"5.3","c":2},
{"x":43,"y":54,"sx":"4.3","sy":"5.4","c":3},
{"x":43,"y":55,"sx":"4.3","sy":"5.5","c":1},
{"x":43,"y":81,"sx":"4.3","sy":"8.1","c":1},
{"x":44,"y":48,"sx":"4.4","sy":"4.8","c":2},
{"x":44,"y":49,"sx":"4.4","sy":"4.9","c":3},
{"x":44,"y":50,"sx":"4.4","sy":"5.0","c":9},
{"x":44,"y":51,"sx":"4.4","sy":"5.1","c":107},
{"x":44,"y":52,"sx":"4.4","sy":"5.2","c":101},
{"x":44,"y":53,"sx":"4.4","sy":"5.3","c":6},
{"x":44,"y":58,"sx":"4.4","sy":"5.8","c":2},
{"x":44,"y":93,"sx":"4.4","sy":"9.3","c":1},
{"x":45,"y":46,"sx":"4.5","sy":"4.6","c":1},
{"x":45,"y":48,"sx":"4.5","sy":"4.8","c":2},
{"x":45,"y":49,"sx":"4.5","sy":"4.9","c":9},
{"x":45,"y":50,"sx":"4.5","sy":"5.0","c":17},
{"x":45,"y":51,"sx":"4.5","sy":"5.1","c":198},
{"x":45,"y":52,"sx":"4.5","sy":"5.2","c":184},
{"x":45,"y":53,"sx":"4.5","sy":"5.3","c":7},
{"x":45,"y":54,"sx":"4.5","sy":"5.4","c":1},
{"x":45,"y":55,"sx":"4.5","sy":"5.5","c":1},
{"x":45,"y":56,"sx":"4.5","sy":"5.6","c":1},
{"x":45,"y":63,"sx":"4.5","sy":"6.3","c":1},
{"x":46,"y":49,"sx":"4.6","sy":"4.9","c":7},
{"x":46,"y":50,"sx":"4.6","sy":"5.0","c":25},
{"x":46,"y":51,"sx":"4.6","sy":"5.1","c":343},
{"x":46,"y":52,"sx":"4.6","sy":"5.2","c":253},
{"x":46,"y":53,"sx":"4.6","sy":"5.3","c":4},
{"x":46,"y":55,"sx":"4.6","sy":"5.5","c":3},
{"x":47,"y":48,"sx":"4.7","sy":"4.8","c":1},
{"x":47,"y":49,"sx":"4.7","sy":"4.9","c":3},
{"x":47,"y":50,"sx":"4.7","sy":"5.0","c":49},
{"x":47,"y":51,"sx":"4.7","sy":"5.1","c":520},
{"x":47,"y":52,"sx":"4.7","sy":"5.2","c":404},
{"x":47,"y":53,"sx":"4.7","sy":"5.3","c":24},
{"x":47,"y":54,"sx":"4.7","sy":"5.4","c":2},
{"x":47,"y":83,"sx":"4.7","sy":"8.3","c":1},
{"x":47,"y":95,"sx":"4.7","sy":"9.5","c":1},
{"x":47,"y":96,"sx":"4.7","sy":"9.6","c":1},
{"x":48,"y":49,"sx":"4.8","sy":"4.9","c":2},
{"x":48,"y":50,"sx":"4.8","sy":"5.0","c":68},
{"x":48,"y":51,"sx":"4.8","sy":"5.1","c":576},
{"x":48,"y":52,"sx":"4.8","sy":"5.2","c":561},
{"x":48,"y":53,"sx":"4.8","sy":"5.3","c":48},
{"x":48,"y":54,"sx":"4.8","sy":"5.4","c":1},
{"x":49,"y":50,"sx":"4.9","sy":"5.0","c":27},
{"x":49,"y":51,"sx":"4.9","sy":"5.1","c":454},
{"x":49,"y":52,"sx":"4.9","sy":"5.2","c":529},
{"x":49,"y":53,"sx":"4.9","sy":"5.3","c":73},
{"x":49,"y":54,"sx":"4.9","sy":"5.4","c":2},
{"x":49,"y":66,"sx":"4.9","sy":"6.6","c":1},
{"x":49,"y":69,"sx":"4.9","sy":"6.9","c":1},
{"x":49,"y":73,"sx":"4.9","sy":"7.3","c":1},
{"x":50,"y":50,"sx":"5.0","sy":"5.0","c":9},
{"x":50,"y":51,"sx":"5.0","sy":"5.1","c":272},
{"x":50,"y":52,"sx":"5.0","sy":"5.2","c":426},
{"x":50,"y":53,"sx":"5.0","sy":"5.3","c":87},
{"x":50,"y":71,"sx":"5.0","sy":"7.1","c":2},
{"x":51,"y":51,"sx":"5.1","sy":"5.1","c":63},
{"x":51,"y":52,"sx":"5.1","sy":"5.2","c":236},
{"x":51,"y":53,"sx":"5.1","sy":"5.3","c":73},
{"x":51,"y":54,"sx":"5.1","sy":"5.4","c":2},
{"x":51,"y":64,"sx":"5.1","sy":"6.4","c":1},
{"x":51,"y":70,"sx":"5.1","sy":"7.0","c":1},
{"x":52,"y":52,"sx":"5.2","sy":"5.2","c":28},
{"x":52,"y":53,"sx":"5.2","sy":"5.3","c":23},
{"x":52,"y":91,"sx":"5.2","sy":"9.1","c":1},
{"x":53,"y":53,"sx":"5.3","sy":"5.3","c":1},
{"x":53,"y":76,"sx":"5.3","sy":"7.6","c":1},
{"x":53,"y":92,"sx":"5.3","sy":"9.2","c":1},
{"x":54,"y":84,"sx":"5.4","sy":"8.4","c":1},
{"x":55,"y":89,"sx":"5.5","sy":"8.9","c":1},
{"x":57,"y":83,"sx":"5.7","sy":"8.3","c":1},
{"x":58,"y":78,"sx":"5.8","sy":"7.8","c":1},
{"x":61,"y":76,"sx":"6.1","sy":"7.6","c":1},
{"x":61,"y":99,"sx":"6.1","sy":"9.9","c":1},
{"x":68,"y":97,"sx":"6.8","sy":"9.7","c":1},
{"x":69,"y":78,"sx":"6.9","sy":"7.8","c":1},
{"x":75,"y":89,"sx":"7.5","sy":"8.9","c":1},
{"x":76,"y":90,"sx":"7.6","sy":"9.0","c":1},
{"x":77,"y":90,"sx":"7.7","sy":"9.0","c":1},
{"x":79,"y":90,"sx":"7.9","sy":"9.0","c":1},
{"x":82,"y":87,"sx":"8.2","sy":"8.7","c":1},
{"x":84,"y":87,"sx":"8.4","sy":"8.7","c":1}]